{
  "date_iso": "2026-06-10",
  "lunar_cn": "四月廿五",
  "zodiac_cn": "馬",
  "solar_term_cn": "—",
  "yi": [
    {
      "zh": "整理思緒",
      "en": "Organize thoughts",
      "fi": "Järjestä ajatukset"
    },
    {
      "zh": "友善交流",
      "en": "Friendly communication",
      "fi": "Ystävällinen viestintä"
    },
    {
      "zh": "靜心片刻",
      "en": "Moment of calm",
      "fi": "Hetki rauhaa"
    }
  ],
  "ji": [
    {
      "zh": "急躁行事",
      "en": "Act impulsively",
      "fi": "Toimia impulsiivisesti"
    },
    {
      "zh": "埋頭苦幹",
      "en": "Overwork yourself",
      "fi": "Ylityskannustaminen"
    },
    {
      "zh": "負面抱怨",
      "en": "Negative complaining",
      "fi": "Negatiivinen valitus"
    }
  ],
  "note_zh": "週中宜放慢節奏，覺察身心，為餘下日子儲蓄能量。",
  "note_en": "Mid-week is good for slowing down, being mindful, and saving energy for the rest of the week.",
  "note_fi": "Keskiviikkona on hyvä hidastaa, olla tietoinen ja kerätä energiaa loppuviikkoon."
}